obeliks/__init__.py
obeliks/rules.py
obeliks/tokenizer.py
obeliks/res/ListOAll.txt
obeliks/res/ListOAllCS.txt
obeliks/res/ListOExcl.txt
obeliks/res/ListOExclCS.txt
obeliks/res/ListONoSegSeq.txt
obeliks/res/ListOSeg.txt
obeliks/res/ListOSegSeq.txt
obeliks/res/ListOSeq.txt
obeliks/res/TokRulesPart1.txt
obeliks/res/TokRulesPart2.txt
obeliks/res/TokRulesPart3.txt
obeliks-1.1.6.data/scripts/obeliks
obeliks-1.1.6.dist-info/LICENSE
obeliks-1.1.6.dist-info/METADATA
obeliks-1.1.6.dist-info/WHEEL
obeliks-1.1.6.dist-info/top_level.txt
obeliks-1.1.6.dist-info/RECORD
