Metadata-Version: 2.1
Name: obeliks
Version: 1.1.6
Summary: Sentence splitting & tokenization
Home-page: https://www.github.com/clarinsi/obeliks
Author: CLARIN.SI
License-File: LICENSE
Requires-Dist: lxml
Requires-Dist: regex
